setup.py
okscraper_django/__init__.py
okscraper_django/admin.py
okscraper_django/models.py
okscraper_django/urls.py
okscraper_django.egg-info/PKG-INFO
okscraper_django.egg-info/SOURCES.txt
okscraper_django.egg-info/dependency_links.txt
okscraper_django.egg-info/pbr.json
okscraper_django.egg-info/requires.txt
okscraper_django.egg-info/top_level.txt
okscraper_django/django_migrations/0001_initial.py
okscraper_django/django_migrations/__init__.py
okscraper_django/management/__init__.py
okscraper_django/management/base_commands.py
okscraper_django/management/tests.py
okscraper_django/management/commands/__init__.py
okscraper_django/management/commands/okscrape.py
okscraper_django/migrations/0001_initial.py
okscraper_django/migrations/0002_auto__chg_field_scraperrunlog_time.py
okscraper_django/migrations/0003_auto__chg_field_scraperrun_scraper_label.py
okscraper_django/migrations/__init__.py
okscraper_django/tests/__init__.py
okscraper_django/tests/scrapers.py
okscraper_django/tests/testManagement.py