Metadata-Version: 1.0
Name: okscraper-django
Version: 0.0.12
Summary: okscraper django integration
Home-page: https://github.com/orihoch/okscraper-django
Author: Ori Hoch
Author-email: ori@uumpa.com
License: GPLv3
Platform: UNKNOWN
